<?xml version="1.0" encoding="UTF-8" ?>
<!DOCTYPE mapper
        PUBLIC "-//mybatis.org//DTD Mapper 3.0//EN"
        "http://mybatis.org/dtd/mybatis-3-mapper.dtd">
<mapper namespace="cum.mapper.MultipleDelAndInsert">
    <!--foreach中标签的作用
    collection:设置需要循环的集合或数组
    item:集合或数组中的每一个数据
    separator:循环体之间的分隔符
    open和close:以什么开始以什么结束-->
    <!--第一种当sql为in时候-->
    <!--<delete id="deleteMoreByArray">
        delete from employee where e_id in
        /*item表示集合中的每一条数据
          open以什么开始
          close以什么结束*/
        <foreach collection="eids" item="eid" separator="," open="(" close=")">
            #{eid}
        </foreach>
    </delete>!-->
    <!--第二种当sql为or时候-->
    <delete id="deleteMoreByArray">
        delete from employee where
        <foreach collection="eids" item="eid" separator="or">
            e_id = #{eid}
        </foreach>
    </delete>
    
    <insert id="insertMoreByList" >
        insert into employee values
        <foreach collection="emps" item="emp" separator=",">
            (null,#{emp.e_name},#{emp.age},#{emp.sex},#{emp.email},null)
        </foreach>
    </insert>
</mapper>
    